jumpstarter_driver_uboot/__init__.py
jumpstarter_driver_uboot/client.py
jumpstarter_driver_uboot/common.py
jumpstarter_driver_uboot/driver.py
jumpstarter_driver_uboot/driver_test.py
jumpstarter_driver_uboot/py.typed
jumpstarter_driver_uboot-0.7.4.dist-info/METADATA
jumpstarter_driver_uboot-0.7.4.dist-info/WHEEL
jumpstarter_driver_uboot-0.7.4.dist-info/RECORD
