Metadata-Version: 2.4
Name: jumpstarter-driver-uboot
Version: 0.7.4
Project-URL: Homepage, https://jumpstarter.dev
Project-URL: source_archive, https://github.com/jumpstarter-dev/repo/archive/c5d38de69eadbb8eb0388bcfe3430a679fff0059.zip
Author-email: Nick Cao <ncao@redhat.com>, Miguel Angel Ajo Pelayo <majopela@redhat.com>, Kirk Brauer <kbrauer@hatci.com>
License-Expression: Apache-2.0
Requires-Python: >=3.11
Requires-Dist: jumpstarter-driver-composite==0.7.4
Requires-Dist: jumpstarter==0.7.4
Requires-Dist: pexpect>=4.9.0
